axmp_openapi_helper/__init__.py
axmp_openapi_helper/multi_openapi_helper.py
axmp_openapi_helper/openapi/axmp_api_models.py
axmp_openapi_helper/openapi/multi_openapi_spec.py
axmp_openapi_helper/openapi/operation.py
axmp_openapi_helper/openapi/fastapi/openapi_models.py
axmp_openapi_helper/utils/converter.py
axmp_openapi_helper/wrapper/api_wrapper.py
axmp_openapi_helper-0.2.0.dist-info/METADATA
axmp_openapi_helper-0.2.0.dist-info/WHEEL
axmp_openapi_helper-0.2.0.dist-info/licenses/LICENSE
axmp_openapi_helper-0.2.0.dist-info/RECORD
