Metadata-Version: 2.4
Name: axmp-openapi-helper
Version: 0.2.0
Summary: This is a openapi helper library for the ZMP AI Platform
Project-URL: homepage, https://github.com/cloudz-mp
Project-URL: repository, https://github.com/cloudz-mp/axmp-openapi-helper
Project-URL: documentation, https://github.com/cloudz-mp/axmp-openapi-helper
Project-URL: Bug Tracker, https://github.com/cloudz-mp/axmp-openapi-helper/issues
Author-email: Kilsoo Kang <kilsoo75@gmail.com>
License-File: LICENSE
Requires-Python: <4.0,>=3.12
Requires-Dist: colorlog>=6.9.0
Requires-Dist: httpx>=0.28.1
Requires-Dist: pydantic>=2.11.7
Requires-Dist: python-dotenv>=1.1.1
